{
  "luis_schema_version": "2.1.0",
  "versionId": "0.1",
  "name": "voice_to_text",
  "desc": "",
  "culture": "en-us",
  "intents": [
    {
      "name": "Filter"
    },
    {
      "name": "Interact"
    },
    {
      "name": "None"
    },
    {
      "name": "Select"
    }
  ],
  "entities": [
    {
      "name": "Academic Year"
    },
    {
      "name": "Aging Days"
    },
    {
      "name": "Basin"
    },
    {
      "name": "Cycle Number"
    },
    {
      "name": "Dashboard"
    },
    {
      "name": "Gender"
    },
    {
      "name": "Module"
    },
    {
      "name": "Product"
    },
    {
      "name": "Region"
    },
    {
      "name": "State"
    },
    {
      "name": "Storm Name"
    },
    {
      "name": "Trend View By"
    },
    {
      "name": "Year"
    }
  ],
  "composites": [],
  "closedLists": [],
  "bing_entities": [],
  "actions": [],
  "model_features": [],
  "regex_features": [],
  "utterances": [
    {
      "text": "filter central region",
      "intent": "Interact",
      "entities": [
        {
          "entity": "Region",
          "startPos": 7,
          "endPos": 13
        }
      ]
    },
    {
      "text": "show me the storm dashboard for alex",
      "intent": "Filter",
      "entities": [
        {
          "entity": "Dashboard",
          "startPos": 12,
          "endPos": 16
        },
        {
          "entity": "Storm Name",
          "startPos": 32,
          "endPos": 35
        }
      ]
    },
    {
      "text": "show me the sales dashboard",
      "intent": "Select",
      "entities": [
        {
          "entity": "Dashboard",
          "startPos": 12,
          "endPos": 16
        }
      ]
    },
    {
      "text": "show me the storm dashboard",
      "intent": "Select",
      "entities": [
        {
          "entity": "Dashboard",
          "startPos": 12,
          "endPos": 16
        }
      ]
    },
    {
      "text": "can you pull out the latest sales dashboad",
      "intent": "Select",
      "entities": [
        {
          "entity": "Dashboard",
          "startPos": 28,
          "endPos": 32
        }
      ]
    },
    {
      "text": "can you show the storm dashboard",
      "intent": "Select",
      "entities": [
        {
          "entity": "Dashboard",
          "startPos": 17,
          "endPos": 21
        }
      ]
    },
    {
      "text": "can you show me the sales dashboard",
      "intent": "Select",
      "entities": [
        {
          "entity": "Dashboard",
          "startPos": 20,
          "endPos": 24
        }
      ]
    },
    {
      "text": "show the sales dashboard for south region",
      "intent": "Filter",
      "entities": [
        {
          "entity": "Region",
          "startPos": 29,
          "endPos": 33
        },
        {
          "entity": "Dashboard",
          "startPos": 9,
          "endPos": 13
        }
      ]
    },
    {
      "text": "show the sales dashboard for west",
      "intent": "Filter",
      "entities": [
        {
          "entity": "Region",
          "startPos": 29,
          "endPos": 32
        },
        {
          "entity": "Dashboard",
          "startPos": 9,
          "endPos": 13
        }
      ]
    },
    {
      "text": "show the sales dashboard for east",
      "intent": "Filter",
      "entities": [
        {
          "entity": "Region",
          "startPos": 29,
          "endPos": 32
        },
        {
          "entity": "Dashboard",
          "startPos": 9,
          "endPos": 13
        }
      ]
    },
    {
      "text": "show me the sales dashboard for central",
      "intent": "Filter",
      "entities": [
        {
          "entity": "Region",
          "startPos": 32,
          "endPos": 38
        },
        {
          "entity": "Dashboard",
          "startPos": 12,
          "endPos": 16
        }
      ]
    },
    {
      "text": "show the storms dashboard for atlantic basin",
      "intent": "Filter",
      "entities": [
        {
          "entity": "Basin",
          "startPos": 30,
          "endPos": 37
        },
        {
          "entity": "Dashboard",
          "startPos": 9,
          "endPos": 14
        }
      ]
    },
    {
      "text": "show me the storm dashboard for colin",
      "intent": "Filter",
      "entities": [
        {
          "entity": "Dashboard",
          "startPos": 12,
          "endPos": 16
        },
        {
          "entity": "Storm Name",
          "startPos": 32,
          "endPos": 36
        }
      ]
    },
    {
      "text": "show me the storm dashboard for bonnie",
      "intent": "Filter",
      "entities": [
        {
          "entity": "Dashboard",
          "startPos": 12,
          "endPos": 16
        },
        {
          "entity": "Storm Name",
          "startPos": 32,
          "endPos": 37
        }
      ]
    },
    {
      "text": "show the sales dashboard for florida",
      "intent": "Filter",
      "entities": [
        {
          "entity": "State",
          "startPos": 29,
          "endPos": 35
        },
        {
          "entity": "Dashboard",
          "startPos": 9,
          "endPos": 13
        }
      ]
    },
    {
      "text": "show the sales dashboard for california",
      "intent": "Filter",
      "entities": [
        {
          "entity": "State",
          "startPos": 29,
          "endPos": 38
        },
        {
          "entity": "Dashboard",
          "startPos": 9,
          "endPos": 13
        }
      ]
    },
    {
      "text": "show the sales dashboard for arizona",
      "intent": "Filter",
      "entities": [
        {
          "entity": "State",
          "startPos": 29,
          "endPos": 35
        },
        {
          "entity": "Dashboard",
          "startPos": 9,
          "endPos": 13
        }
      ]
    },
    {
      "text": "show the storms dashboard for west pacific basin",
      "intent": "Filter",
      "entities": [
        {
          "entity": "Basin",
          "startPos": 30,
          "endPos": 41
        },
        {
          "entity": "Dashboard",
          "startPos": 9,
          "endPos": 14
        }
      ]
    },
    {
      "text": "show the storms dashboard for east pacific basin",
      "intent": "Filter",
      "entities": [
        {
          "entity": "Basin",
          "startPos": 30,
          "endPos": 41
        },
        {
          "entity": "Dashboard",
          "startPos": 9,
          "endPos": 14
        }
      ]
    },
    {
      "text": "show the storms dashboard for atlantic",
      "intent": "Filter",
      "entities": [
        {
          "entity": "Basin",
          "startPos": 30,
          "endPos": 37
        },
        {
          "entity": "Dashboard",
          "startPos": 9,
          "endPos": 14
        }
      ]
    },
    {
      "text": "show me the storms dashboard for alex",
      "intent": "Filter",
      "entities": [
        {
          "entity": "Dashboard",
          "startPos": 12,
          "endPos": 17
        },
        {
          "entity": "Storm Name",
          "startPos": 33,
          "endPos": 36
        }
      ]
    },
    {
      "text": "which storms affected east pacific in 2011 ?",
      "intent": "Filter",
      "entities": [
        {
          "entity": "Basin",
          "startPos": 22,
          "endPos": 33
        },
        {
          "entity": "Year",
          "startPos": 38,
          "endPos": 41
        },
        {
          "entity": "Dashboard",
          "startPos": 6,
          "endPos": 11
        }
      ]
    },
    {
      "text": "how alex affected east pacific",
      "intent": "Filter",
      "entities": [
        {
          "entity": "Basin",
          "startPos": 18,
          "endPos": 29
        },
        {
          "entity": "Storm Name",
          "startPos": 4,
          "endPos": 7
        }
      ]
    },
    {
      "text": "show me the storms dashboard for alex in atlantic",
      "intent": "Filter",
      "entities": [
        {
          "entity": "Basin",
          "startPos": 41,
          "endPos": 48
        },
        {
          "entity": "Dashboard",
          "startPos": 12,
          "endPos": 17
        },
        {
          "entity": "Storm Name",
          "startPos": 33,
          "endPos": 36
        }
      ]
    },
    {
      "text": "show me the college dashboard for men in 2013",
      "intent": "Filter",
      "entities": [
        {
          "entity": "Dashboard",
          "startPos": 12,
          "endPos": 18
        },
        {
          "entity": "Gender",
          "startPos": 34,
          "endPos": 36
        },
        {
          "entity": "Academic Year",
          "startPos": 41,
          "endPos": 44
        }
      ]
    },
    {
      "text": "show me the college dashboard for 2013 and 2014",
      "intent": "Filter",
      "entities": [
        {
          "entity": "Dashboard",
          "startPos": 12,
          "endPos": 18
        },
        {
          "entity": "Academic Year",
          "startPos": 34,
          "endPos": 37
        },
        {
          "entity": "Academic Year",
          "startPos": 43,
          "endPos": 46
        }
      ]
    },
    {
      "text": "show me the college dashboard for men",
      "intent": "Filter",
      "entities": [
        {
          "entity": "Dashboard",
          "startPos": 12,
          "endPos": 18
        },
        {
          "entity": "Gender",
          "startPos": 34,
          "endPos": 36
        }
      ]
    },
    {
      "text": "show me the college dashboard for 2014",
      "intent": "Filter",
      "entities": [
        {
          "entity": "Dashboard",
          "startPos": 12,
          "endPos": 18
        },
        {
          "entity": "Academic Year",
          "startPos": 34,
          "endPos": 37
        }
      ]
    },
    {
      "text": "select alex",
      "intent": "Interact",
      "entities": [
        {
          "entity": "Storm Name",
          "startPos": 7,
          "endPos": 10
        }
      ]
    },
    {
      "text": "filter west pacific",
      "intent": "Interact",
      "entities": [
        {
          "entity": "Basin",
          "startPos": 7,
          "endPos": 18
        }
      ]
    },
    {
      "text": "filter east pacific",
      "intent": "Interact",
      "entities": [
        {
          "entity": "Basin",
          "startPos": 7,
          "endPos": 18
        }
      ]
    },
    {
      "text": "select bonnie",
      "intent": "Interact",
      "entities": [
        {
          "entity": "Storm Name",
          "startPos": 7,
          "endPos": 12
        }
      ]
    },
    {
      "text": "filter south region",
      "intent": "Interact",
      "entities": [
        {
          "entity": "Region",
          "startPos": 7,
          "endPos": 11
        }
      ]
    },
    {
      "text": "select california",
      "intent": "Interact",
      "entities": [
        {
          "entity": "State",
          "startPos": 7,
          "endPos": 16
        }
      ]
    },
    {
      "text": "select arizona",
      "intent": "Interact",
      "entities": [
        {
          "entity": "State",
          "startPos": 7,
          "endPos": 13
        }
      ]
    },
    {
      "text": "sales distribution across channels till date for product 1",
      "intent": "Filter",
      "entities": [
        {
          "entity": "Dashboard",
          "startPos": 0,
          "endPos": 17
        },
        {
          "entity": "Product",
          "startPos": 49,
          "endPos": 57
        }
      ]
    },
    {
      "text": "sales across geographies for product 1",
      "intent": "Filter",
      "entities": [
        {
          "entity": "Dashboard",
          "startPos": 13,
          "endPos": 23
        },
        {
          "entity": "Product",
          "startPos": 29,
          "endPos": 37
        }
      ]
    },
    {
      "text": "retailers having negative trend for product one",
      "intent": "Filter",
      "entities": [
        {
          "entity": "Dashboard",
          "startPos": 17,
          "endPos": 30
        }
      ]
    },
    {
      "text": "retailers having positive trend for product one",
      "intent": "Filter",
      "entities": [
        {
          "entity": "Dashboard",
          "startPos": 17,
          "endPos": 30
        }
      ]
    },
    {
      "text": "open storms",
      "intent": "Select",
      "entities": [
        {
          "entity": "Dashboard",
          "startPos": 5,
          "endPos": 10
        }
      ]
    },
    {
      "text": "open sales",
      "intent": "Select",
      "entities": [
        {
          "entity": "Dashboard",
          "startPos": 5,
          "endPos": 9
        }
      ]
    },
    {
      "text": "show me the mobile dashboard for east region",
      "intent": "Filter",
      "entities": [
        {
          "entity": "Region",
          "startPos": 33,
          "endPos": 36
        },
        {
          "entity": "Dashboard",
          "startPos": 12,
          "endPos": 17
        }
      ]
    },
    {
      "text": "open mobile dashboard",
      "intent": "Select",
      "entities": [
        {
          "entity": "Dashboard",
          "startPos": 5,
          "endPos": 10
        }
      ]
    },
    {
      "text": "open mobile",
      "intent": "Select",
      "entities": [
        {
          "entity": "Dashboard",
          "startPos": 5,
          "endPos": 10
        }
      ]
    },
    {
      "text": "show mobile dashboard",
      "intent": "Select",
      "entities": [
        {
          "entity": "Dashboard",
          "startPos": 5,
          "endPos": 10
        }
      ]
    },
    {
      "text": "show me the mobile dashboard",
      "intent": "Select",
      "entities": [
        {
          "entity": "Dashboard",
          "startPos": 12,
          "endPos": 17
        }
      ]
    },
    {
      "text": "show me the retailers having negative trend",
      "intent": "Select",
      "entities": [
        {
          "entity": "Dashboard",
          "startPos": 29,
          "endPos": 42
        }
      ]
    },
    {
      "text": "show me the retailers having positive trend",
      "intent": "Select",
      "entities": [
        {
          "entity": "Dashboard",
          "startPos": 29,
          "endPos": 42
        }
      ]
    },
    {
      "text": "show me the sales distribution across channels till date",
      "intent": "Select",
      "entities": [
        {
          "entity": "Dashboard",
          "startPos": 12,
          "endPos": 29
        }
      ]
    },
    {
      "text": "open the sales distribution dashboard",
      "intent": "Select",
      "entities": [
        {
          "entity": "Dashboard",
          "startPos": 9,
          "endPos": 26
        }
      ]
    },
    {
      "text": "open sales distribution dashboard",
      "intent": "Select",
      "entities": [
        {
          "entity": "Dashboard",
          "startPos": 5,
          "endPos": 22
        }
      ]
    },
    {
      "text": "show me the sales across geographies",
      "intent": "Select",
      "entities": [
        {
          "entity": "Dashboard",
          "startPos": 25,
          "endPos": 35
        }
      ]
    },
    {
      "text": "open the mobile dashboard for east region",
      "intent": "Filter",
      "entities": [
        {
          "entity": "Region",
          "startPos": 30,
          "endPos": 33
        },
        {
          "entity": "Dashboard",
          "startPos": 9,
          "endPos": 14
        }
      ]
    },
    {
      "text": "open the patient dashboard for cycle three",
      "intent": "Filter",
      "entities": [
        {
          "entity": "Cycle Number",
          "startPos": 37,
          "endPos": 41
        },
        {
          "entity": "Dashboard",
          "startPos": 9,
          "endPos": 15
        }
      ]
    },
    {
      "text": "show me the patient dashboard for cycle two",
      "intent": "Filter",
      "entities": [
        {
          "entity": "Cycle Number",
          "startPos": 40,
          "endPos": 42
        },
        {
          "entity": "Dashboard",
          "startPos": 12,
          "endPos": 18
        }
      ]
    },
    {
      "text": "show me the patient dashboard for cycle one",
      "intent": "Filter",
      "entities": [
        {
          "entity": "Cycle Number",
          "startPos": 40,
          "endPos": 42
        },
        {
          "entity": "Dashboard",
          "startPos": 12,
          "endPos": 18
        }
      ]
    },
    {
      "text": "filter cycle one",
      "intent": "Interact",
      "entities": [
        {
          "entity": "Cycle Number",
          "startPos": 13,
          "endPos": 15
        }
      ]
    },
    {
      "text": "select consumer products",
      "intent": "Interact",
      "entities": [
        {
          "entity": "Module",
          "startPos": 7,
          "endPos": 23
        }
      ]
    },
    {
      "text": "can you give me a summary of incidents in september 2017",
      "intent": "Filter",
      "entities": [
        {
          "entity": "Dashboard",
          "startPos": 29,
          "endPos": 37
        }
      ]
    },
    {
      "text": "can you show me the incident summary for consumer products",
      "intent": "Filter",
      "entities": [
        {
          "entity": "Dashboard",
          "startPos": 20,
          "endPos": 35
        },
        {
          "entity": "Module",
          "startPos": 41,
          "endPos": 57
        }
      ]
    },
    {
      "text": "show me the incidents trend for consumer products",
      "intent": "Filter",
      "entities": [
        {
          "entity": "Dashboard",
          "startPos": 12,
          "endPos": 26
        },
        {
          "entity": "Module",
          "startPos": 32,
          "endPos": 48
        }
      ]
    },
    {
      "text": "can you give me a summary of incidents for september",
      "intent": "Filter",
      "entities": [
        {
          "entity": "Dashboard",
          "startPos": 29,
          "endPos": 37
        }
      ]
    },
    {
      "text": "can you give me a summary of the incidents",
      "intent": "Filter",
      "entities": [
        {
          "entity": "Dashboard",
          "startPos": 33,
          "endPos": 41
        }
      ]
    },
    {
      "text": "let's now check on the service requests",
      "intent": "Filter",
      "entities": [
        {
          "entity": "Dashboard",
          "startPos": 23,
          "endPos": 38
        }
      ]
    },
    {
      "text": "show me the service request",
      "intent": "Filter",
      "entities": [
        {
          "entity": "Dashboard",
          "startPos": 12,
          "endPos": 26
        }
      ]
    },
    {
      "text": "can you show me the service request",
      "intent": "Filter",
      "entities": [
        {
          "entity": "Dashboard",
          "startPos": 20,
          "endPos": 34
        }
      ]
    },
    {
      "text": "please show me the incident resolution metrics",
      "intent": "Filter",
      "entities": [
        {
          "entity": "Dashboard",
          "startPos": 19,
          "endPos": 37
        }
      ]
    },
    {
      "text": "can you show the effort variance for change",
      "intent": "Filter",
      "entities": [
        {
          "entity": "Dashboard",
          "startPos": 17,
          "endPos": 31
        }
      ]
    },
    {
      "text": "can you show me the tickets having aging greater than 60 days",
      "intent": "Filter",
      "entities": [
        {
          "entity": "Aging Days",
          "startPos": 41,
          "endPos": 55
        },
        {
          "entity": "Dashboard",
          "startPos": 20,
          "endPos": 26
        }
      ]
    },
    {
      "text": "can you show me the incident history",
      "intent": "Filter",
      "entities": [
        {
          "entity": "Dashboard",
          "startPos": 20,
          "endPos": 35
        }
      ]
    },
    {
      "text": "can you show me the change in effort",
      "intent": "Filter",
      "entities": [
        {
          "entity": "Dashboard",
          "startPos": 20,
          "endPos": 25
        }
      ]
    }
  ]
}